{
  "version": "5",
  "dialect": "sqlite",
  "entries": [
    {
      "idx": 0,
      "version": "5",
      "when": 1694794320410,
      "tag": "0000_graceful_sage",
      "breakpoints": true
    },
    {
      "idx": 1,
      "version": "5",
      "when": 1695563004555,
      "tag": "0001_massive_luckman",
      "breakpoints": true
    },
    {
      "idx": 2,
      "version": "5",
      "when": 1695734911172,
      "tag": "0002_young_cargill",
      "breakpoints": true
    },
    {
      "idx": 3,
      "version": "5",
      "when": 1695738824106,
      "tag": "0003_chilly_mongu",
      "breakpoints": true
    },
    {
      "idx": 4,
      "version": "5",
      "when": 1695823866923,
      "tag": "0004_bouncy_silk_fever",
      "breakpoints": true
    },
    {
      "idx": 5,
      "version": "5",
      "when": 1695826393652,
      "tag": "0005_fresh_texas_twister",
      "breakpoints": true
    },
    {
      "idx": 6,
      "version": "5",
      "when": 1696194631125,
      "tag": "0006_powerful_captain_universe",
      "breakpoints": true
    },
    {
      "idx": 7,
      "version": "5",
      "when": 1696281288549,
      "tag": "0007_useful_psynapse",
      "breakpoints": true
    }
  ]
}